{
  "publicPath": "/_nuxt/",
  "all": [
    "../server/index.spa.html",
    "../server/index.ssr.html",
    "0a3100c339489669dba1.js",
    "0af5d0ab150860e3e852.js",
    "0d469acb952b50d74a51.js",
    "1178d6a16637639c6322.js",
    "3578ba861343c7822af0.js",
    "3acb8a5b88c508215a21.js",
    "3c8c630d76d015350d3d.js",
    "503e96520cc8399a3037.js",
    "50b2eb2ad4a3a87cd04a.js",
    "52c7728e5c2baecebdd8.js",
    "65ac612a5a2cf01a309e.js",
    "66de2dd2e7beaab61fe3.js",
    "66fffd8b7c939dd1aaf4.js",
    "774db39ddff74922fb05.js",
    "7a0733979bbe84a7d86f.js",
    "89d15c7d103b073c2b05.js",
    "9847b64a3b614e0e576e.js",
    "9d4848e03a6dec37f133.js",
    "LICENSES",
    "a43d0debf23d9ea0d825.js",
    "b6dc80c64d13afbe158b.js",
    "b81ccab56f54fcfdad13.js",
    "b93c66e12303cfaf5c87.js",
    "c02fdc94054a51c1a13b.js",
    "c7edbe7565aa4800b1e2.js",
    "c81fe281f7ddf8114954.js",
    "d333d2891aaa1fb920fc.js",
    "f3dcc8362db3072f2d9d.js",
    "f6f3898f57f41ef05482.js",
    "fonts/2569aae.woff",
    "fonts/4264397.woff2",
    "fonts/674f50d.eot",
    "fonts/af7ae50.woff2",
    "fonts/b06871f.ttf",
    "fonts/c173356.eot",
    "fonts/f82ec6b.ttf",
    "fonts/fee66e7.woff",
    "img/0b11abf.svg",
    "img/0b8a30b.svg",
    "img/0c63fd9.svg",
    "img/1a9bd09.svg",
    "img/1d4aa8d.svg",
    "img/344dc1a.svg",
    "img/3adf807.svg",
    "img/3afec8c.svg",
    "img/40a7620.png",
    "img/47d78ae.svg",
    "img/4bb5249.svg",
    "img/4c6f478.svg",
    "img/4c91c65.svg",
    "img/4d5a2d7.svg",
    "img/50c948a.svg",
    "img/5322687.svg",
    "img/54e7811.svg",
    "img/5aeed7a.svg",
    "img/6500725.svg",
    "img/6995293.svg",
    "img/6bf10f1.svg",
    "img/6c2c221.svg",
    "img/6d0cb14.svg",
    "img/6fc602c.svg",
    "img/73c57ed.svg",
    "img/7f2fe55.svg",
    "img/7f306aa.svg",
    "img/832fb46.svg",
    "img/8591df9.svg",
    "img/85e5282.svg",
    "img/897113b.svg",
    "img/912ec66.svg",
    "img/9308eb0.svg",
    "img/982524b.svg",
    "img/99f109b.svg",
    "img/9fa2010.svg",
    "img/9fa59cc.svg",
    "img/a02d8a7.svg",
    "img/a351324.svg",
    "img/a512a4a.svg",
    "img/aac2c23.svg",
    "img/b49eabd.svg",
    "img/b7a0543.svg",
    "img/ba68c9b.svg",
    "img/bd6c017.svg",
    "img/d2c6a82.svg",
    "img/da78b77.svg",
    "img/dc05b61.svg",
    "img/dcc775f.svg",
    "img/e067c66.svg",
    "img/e4f67d1.svg",
    "img/eaa1469.svg",
    "img/ef121aa.svg",
    "img/ef256d1.svg",
    "img/ef7ff6a.svg",
    "img/f3941f3.svg",
    "img/f5d174c.svg",
    "img/f5de326.svg",
    "img/f911b8f.svg",
    "img/fbc846f.svg",
    "img/fc65104.svg",
    "img/fe0e24f.svg",
    "manifest.82ac7373.json"
  ],
  "initial": [
    "f6f3898f57f41ef05482.js",
    "50b2eb2ad4a3a87cd04a.js",
    "0a3100c339489669dba1.js",
    "66fffd8b7c939dd1aaf4.js"
  ],
  "async": [
    "0af5d0ab150860e3e852.js",
    "0d469acb952b50d74a51.js",
    "1178d6a16637639c6322.js",
    "3578ba861343c7822af0.js",
    "3acb8a5b88c508215a21.js",
    "3c8c630d76d015350d3d.js",
    "503e96520cc8399a3037.js",
    "52c7728e5c2baecebdd8.js",
    "65ac612a5a2cf01a309e.js",
    "66de2dd2e7beaab61fe3.js",
    "774db39ddff74922fb05.js",
    "7a0733979bbe84a7d86f.js",
    "89d15c7d103b073c2b05.js",
    "9847b64a3b614e0e576e.js",
    "9d4848e03a6dec37f133.js",
    "a43d0debf23d9ea0d825.js",
    "b6dc80c64d13afbe158b.js",
    "b81ccab56f54fcfdad13.js",
    "b93c66e12303cfaf5c87.js",
    "c02fdc94054a51c1a13b.js",
    "c7edbe7565aa4800b1e2.js",
    "c81fe281f7ddf8114954.js",
    "d333d2891aaa1fb920fc.js",
    "f3dcc8362db3072f2d9d.js"
  ],
  "modules": {
    "32225512": [
      23,
      72,
      73,
      79
    ],
    "64045532": [
      3,
      89,
      83,
      41,
      92,
      81,
      68,
      49,
      65,
      87,
      55,
      42,
      67,
      64,
      50,
      58,
      52,
      91
    ],
    "71930574": [
      10
    ],
    "f9b20d62": [
      10
    ],
    "6dfe7019": [
      2
    ],
    "df4070ea": [
      10
    ],
    "a99f3114": [
      10
    ],
    "a6083f16": [
      2
    ],
    "83da093c": [
      14,
      36,
      51,
      39,
      32,
      31,
      37,
      40,
      33,
      33,
      34,
      38,
      35,
      70
    ],
    "1e13e4b6": [
      10
    ],
    "10bc2036": [
      10
    ],
    "20218f05": [
      10
    ],
    "312f254a": [
      10
    ],
    "36c0c8f3": [
      10
    ],
    "4adeeede": [
      10
    ],
    "837a30a6": [
      2
    ],
    "ca217982": [
      2
    ],
    "05eac95b": [
      10
    ],
    "c7c31980": [
      10
    ],
    "ffd5ab6a": [
      10
    ],
    "c085608c": [
      10
    ],
    "c58bc992": [
      10
    ],
    "2eab82c2": [
      2
    ],
    "2c1065a1": [
      10
    ],
    "ddea69ca": [
      10
    ],
    "ead9e806": [
      10
    ],
    "ca1b3368": [
      10
    ],
    "ecded724": [
      10
    ],
    "cbef9a1a": [
      10
    ],
    "5c02d6e3": [
      10
    ],
    "ed7c1f8a": [
      10
    ],
    "52c85c97": [
      10
    ],
    "4409c15e": [
      10
    ],
    "4b102680": [
      2
    ],
    "10995ecd": [
      10
    ],
    "95166b4c": [
      10
    ],
    "b0b894b6": [
      10
    ],
    "98f7e4e0": [
      10
    ],
    "37d01904": [
      10
    ],
    "6a9facdd": [
      10
    ],
    "571075d5": [
      10
    ],
    "03080368": [
      10
    ],
    "32eea3f5": [
      10
    ],
    "380ad5e0": [
      10
    ],
    "d6abc8b0": [
      10
    ],
    "55d6bc50": [
      10
    ],
    "68c3f90a": [
      10
    ],
    "7fe75d42": [
      10
    ],
    "0d96a248": [
      10
    ],
    "57d476e4": [
      10
    ],
    "6d756420": [
      10
    ],
    "743691a5": [
      14,
      36,
      51,
      39,
      32,
      31,
      37,
      40,
      33,
      33,
      34,
      38,
      35,
      70
    ],
    "12b4c198": [
      14,
      36,
      51,
      39,
      32,
      31,
      37,
      40,
      33,
      33,
      34,
      38,
      35,
      70
    ],
    "156f3461": [
      14,
      36,
      51,
      39,
      32,
      31,
      37,
      40,
      33,
      33,
      34,
      38,
      35,
      70
    ],
    "7f1ab326": [
      14,
      36,
      51,
      39,
      32,
      31,
      37,
      40,
      33,
      33,
      34,
      38,
      35,
      70
    ],
    "1a26abd0": [
      14,
      36,
      51,
      39,
      32,
      31,
      37,
      40,
      33,
      33,
      34,
      38,
      35,
      70
    ],
    "3bef6dbe": [
      10
    ],
    "2f872e1c": [
      10
    ],
    "4c033cf8": [
      10
    ],
    "9e0219e6": [
      10
    ],
    "fd79fc3c": [
      10
    ],
    "aea12698": [
      10
    ],
    "626d2edc": [
      10
    ],
    "51fe2ec8": [
      10
    ],
    "5202ba7e": [
      10
    ],
    "7b2cac98": [
      10
    ],
    "e2205a00": [
      10
    ],
    "4c539ef0": [
      10
    ],
    "e4b5f22e": [
      10
    ],
    "39f99a6c": [
      10
    ],
    "947aa77e": [
      10
    ],
    "c680143a": [
      10
    ],
    "76f1935a": [
      2
    ],
    "0a933641": [
      10
    ],
    "1a31418b": [
      2
    ],
    "9c9ea3b6": [
      10
    ],
    "7d30742b": [
      2
    ],
    "fde930a8": [
      2
    ],
    "29a82e73": [
      14,
      36,
      51,
      39,
      32,
      31,
      37,
      40,
      33,
      33,
      34,
      38,
      35,
      70
    ],
    "df06704a": [
      14,
      36,
      51,
      39,
      32,
      31,
      37,
      40,
      33,
      33,
      34,
      38,
      35,
      70
    ],
    "b26667da": [
      10
    ],
    "56f6aba6": [
      10
    ],
    "6860a5e5": [
      10
    ],
    "f3834d3c": [
      10
    ],
    "bf93322a": [
      10
    ],
    "fd43db5e": [
      10
    ],
    "4d811b1a": [
      10
    ],
    "9efd27a4": [
      10
    ],
    "eacdcb20": [
      10
    ],
    "083130a2": [
      10
    ],
    "a16261fa": [
      10
    ],
    "520bd1ea": [
      10
    ],
    "7d156a71": [
      10
    ],
    "5b66da96": [
      10
    ],
    "76338c66": [
      10
    ],
    "7ce5b221": [
      10
    ],
    "692ddafb": [
      10
    ],
    "0a5e0ba6": [
      10
    ],
    "0b343814": [
      10
    ],
    "959aa4fc": [
      10
    ],
    "6aa6397b": [
      10
    ],
    "997ebcf8": [
      10
    ],
    "781de99b": [
      10
    ],
    "716ec88e": [
      10
    ],
    "7f21549c": [
      14,
      36,
      51,
      39,
      32,
      31,
      37,
      40,
      33,
      33,
      34,
      38,
      35,
      70
    ],
    "ea843f1e": [
      2
    ],
    "6da0847a": [
      14,
      36,
      51,
      39,
      32,
      31,
      37,
      40,
      33,
      33,
      34,
      38,
      35,
      70
    ],
    "42965e9a": [
      14,
      36,
      51,
      39,
      32,
      31,
      37,
      40,
      33,
      33,
      34,
      38,
      35,
      70
    ],
    "36699c1f": [
      10
    ],
    "e31bd62e": [
      10
    ],
    "7a6dcdc4": [
      10
    ],
    "6f1cfd16": [
      10
    ],
    "11f507df": [
      10
    ],
    "7e026684": [
      14,
      36,
      51,
      39,
      32,
      31,
      37,
      40,
      33,
      33,
      34,
      38,
      35,
      70
    ],
    "5a2677d4": [
      14,
      36,
      51,
      39,
      32,
      31,
      37,
      40,
      33,
      33,
      34,
      38,
      35,
      70
    ],
    "bd7f09ea": [
      10
    ],
    "76e9bc0e": [
      2
    ],
    "08a08ac4": [
      2
    ],
    "02a7734a": [
      2
    ],
    "5bb236dc": [
      10
    ],
    "19de1994": [
      10
    ],
    "2ea851d6": [
      2
    ],
    "3f5c012c": [
      2
    ],
    "f3145ee2": [
      2
    ],
    "583a6ee2": [
      2
    ],
    "b3800a3c": [
      2
    ],
    "5d603291": [
      2
    ],
    "913086f6": [
      2
    ],
    "3b09ce68": [
      2
    ],
    "2a516e33": [
      14,
      36,
      51,
      39,
      32,
      31,
      37,
      40,
      33,
      33,
      34,
      38,
      35,
      70
    ],
    "c3ffe530": [
      14,
      36,
      51,
      39,
      32,
      31,
      37,
      40,
      33,
      33,
      34,
      38,
      35,
      70
    ],
    "4afc6131": [
      14,
      36,
      51,
      39,
      32,
      31,
      37,
      40,
      33,
      33,
      34,
      38,
      35,
      70
    ],
    "912898a2": [
      14,
      36,
      51,
      39,
      32,
      31,
      37,
      40,
      33,
      33,
      34,
      38,
      35,
      70
    ],
    "4f59e9f8": [
      10
    ],
    "90e64480": [
      10
    ],
    "5d98f3b2": [
      10
    ],
    "86acd3be": [
      10
    ],
    "c074f0d8": [
      10
    ],
    "701f2a35": [
      10
    ],
    "3eea6326": [
      10
    ],
    "06b3b1e0": [
      10
    ],
    "5e157b08": [
      10
    ],
    "5f5e5d36": [
      10
    ],
    "6cb06174": [
      10
    ],
    "5dccc3d0": [
      10
    ],
    "22ae5cba": [
      10
    ],
    "b87cb0c0": [
      10
    ],
    "067763fe": [
      10
    ],
    "037d26bc": [
      10
    ],
    "5c6a5d86": [
      10
    ],
    "49d6a53c": [
      10
    ],
    "c139107e": [
      10
    ],
    "1a5b228c": [
      10
    ],
    "50af3df4": [
      10
    ],
    "524b0cd6": [
      10
    ],
    "7d1e6177": [
      10
    ],
    "45904ffd": [
      10
    ],
    "75c60366": [
      10
    ],
    "3fdf0335": [
      14,
      36,
      51,
      39,
      32,
      31,
      37,
      40,
      33,
      33,
      34,
      38,
      35,
      70
    ],
    "cd9a7f2a": [
      10
    ],
    "578cc646": [
      10
    ],
    "899dff84": [
      10
    ],
    "284c1172": [
      10
    ],
    "4b33c30e": [
      10
    ],
    "ff262da6": [
      10
    ],
    "27456b8a": [
      10
    ],
    "18ddc350": [
      10
    ],
    "4d694798": [
      10
    ],
    "44d94bde": [
      10
    ],
    "7e9340af": [
      10
    ],
    "53e1b041": [
      2
    ],
    "4ee375a2": [
      10
    ],
    "7141d36a": [
      14,
      36,
      51,
      39,
      32,
      31,
      37,
      40,
      33,
      33,
      34,
      38,
      35,
      70
    ],
    "2d0ba2fe": [
      14,
      36,
      51,
      39,
      32,
      31,
      37,
      40,
      33,
      33,
      34,
      38,
      35,
      70
    ],
    "6852f754": [
      14,
      36,
      51,
      39,
      32,
      31,
      37,
      40,
      33,
      33,
      34,
      38,
      35,
      70
    ],
    "f6e627c6": [
      14,
      36,
      51,
      39,
      32,
      31,
      37,
      40,
      33,
      33,
      34,
      38,
      35,
      70
    ],
    "62ee3042": [
      14,
      36,
      51,
      39,
      32,
      31,
      37,
      40,
      33,
      33,
      34,
      38,
      35,
      70
    ],
    "4d838df0": [
      14,
      36,
      51,
      39,
      32,
      31,
      37,
      40,
      33,
      33,
      34,
      38,
      35,
      70
    ],
    "7f20e2e4": [
      14,
      36,
      51,
      39,
      32,
      31,
      37,
      40,
      33,
      33,
      34,
      38,
      35,
      70
    ],
    "1cf0266a": [
      14,
      36,
      51,
      39,
      32,
      31,
      37,
      40,
      33,
      33,
      34,
      38,
      35,
      70
    ],
    "5c2e034c": [
      14,
      36,
      51,
      39,
      32,
      31,
      37,
      40,
      33,
      33,
      34,
      38,
      35,
      70
    ],
    "6afcf821": [
      14,
      36,
      51,
      39,
      32,
      31,
      37,
      40,
      33,
      33,
      34,
      38,
      35,
      70
    ],
    "76506a5b": [
      14,
      36,
      51,
      39,
      32,
      31,
      37,
      40,
      33,
      33,
      34,
      38,
      35,
      70
    ],
    "6e539fbc": [
      14,
      36,
      51,
      39,
      32,
      31,
      37,
      40,
      33,
      33,
      34,
      38,
      35,
      70
    ],
    "2622d8eb": [
      14,
      36,
      51,
      39,
      32,
      31,
      37,
      40,
      33,
      33,
      34,
      38,
      35,
      70
    ],
    "c39c048e": [
      14,
      36,
      51,
      39,
      32,
      31,
      37,
      40,
      33,
      33,
      34,
      38,
      35,
      70
    ],
    "4d2ff192": [
      14,
      36,
      51,
      39,
      32,
      31,
      37,
      40,
      33,
      33,
      34,
      38,
      35,
      70
    ],
    "8e81bd54": [
      14,
      36,
      51,
      39,
      32,
      31,
      37,
      40,
      33,
      33,
      34,
      38,
      35,
      70
    ],
    "a245e690": [
      2
    ],
    "3c0bc468": [
      14,
      36,
      51,
      39,
      32,
      31,
      37,
      40,
      33,
      33,
      34,
      38,
      35,
      70
    ],
    "0f109dd3": [
      14,
      36,
      51,
      39,
      32,
      31,
      37,
      40,
      33,
      33,
      34,
      38,
      35,
      70
    ],
    "4649ca65": [
      14,
      36,
      51,
      39,
      32,
      31,
      37,
      40,
      33,
      33,
      34,
      38,
      35,
      70
    ],
    "7d11d65c": [
      14,
      36,
      51,
      39,
      32,
      31,
      37,
      40,
      33,
      33,
      34,
      38,
      35,
      70
    ],
    "420c30a5": [
      14,
      36,
      51,
      39,
      32,
      31,
      37,
      40,
      33,
      33,
      34,
      38,
      35,
      70
    ],
    "6eaddd60": [
      2
    ],
    "1f75e74c": [
      14,
      36,
      51,
      39,
      32,
      31,
      37,
      40,
      33,
      33,
      34,
      38,
      35,
      70
    ],
    "5c9b954d": [
      14,
      36,
      51,
      39,
      32,
      31,
      37,
      40,
      33,
      33,
      34,
      38,
      35,
      70
    ],
    "0594a5f2": [
      14,
      36,
      51,
      39,
      32,
      31,
      37,
      40,
      33,
      33,
      34,
      38,
      35,
      70
    ],
    "51df188c": [
      14,
      36,
      51,
      39,
      32,
      31,
      37,
      40,
      33,
      33,
      34,
      38,
      35,
      70
    ],
    "3f8f5702": [
      10
    ],
    "5b0ead77": [
      10
    ],
    "b07a9110": [
      10
    ],
    "58e2e440": [
      10
    ],
    "6af94113": [
      14,
      36,
      51,
      39,
      32,
      31,
      37,
      40,
      33,
      33,
      34,
      38,
      35,
      70
    ],
    "bcf89a80": [
      14,
      36,
      51,
      39,
      32,
      31,
      37,
      40,
      33,
      33,
      34,
      38,
      35,
      70
    ],
    "314a5136": [
      10
    ],
    "06f09de5": [
      10
    ],
    "94ef234c": [
      10
    ],
    "1bdee40d": [
      10
    ],
    "ed62111a": [
      10
    ],
    "9f9e3db8": [
      10
    ],
    "4221f73b": [
      10
    ],
    "d2d2836e": [
      10
    ],
    "26504a7e": [
      10
    ],
    "493ba558": [
      10
    ],
    "8f2ff93a": [
      10
    ],
    "7b958b36": [
      10
    ],
    "e844e34a": [
      10
    ],
    "77dbc70c": [
      10
    ],
    "0d751738": [
      10
    ],
    "d60cc5a2": [
      10
    ],
    "8cb1ced4": [
      10
    ],
    "6b81242e": [
      10
    ],
    "3b943f1a": [
      14,
      36,
      51,
      39,
      32,
      31,
      37,
      40,
      33,
      33,
      34,
      38,
      35,
      70
    ],
    "1c20e480": [
      14,
      36,
      51,
      39,
      32,
      31,
      37,
      40,
      33,
      33,
      34,
      38,
      35,
      70
    ],
    "7d17a4ad": [
      14,
      36,
      51,
      39,
      32,
      31,
      37,
      40,
      33,
      33,
      34,
      38,
      35,
      70
    ],
    "cad199f6": [
      2
    ],
    "4c09b6ab": [
      2
    ],
    "4a6e7778": [
      2
    ],
    "3c237d11": [
      2
    ],
    "2b2f47ea": [
      14,
      36,
      51,
      39,
      32,
      31,
      37,
      40,
      33,
      33,
      34,
      38,
      35,
      70
    ],
    "e6a550d2": [
      14,
      36,
      51,
      39,
      32,
      31,
      37,
      40,
      33,
      33,
      34,
      38,
      35,
      70
    ],
    "1d748930": [
      14,
      36,
      51,
      39,
      32,
      31,
      37,
      40,
      33,
      33,
      34,
      38,
      35,
      70
    ],
    "218d65d8": [
      2
    ],
    "0b5f7726": [
      22
    ],
    "20b69e21": [
      16,
      90,
      46,
      47
    ],
    "629ddd65": [
      23,
      72,
      73,
      79
    ],
    "1e6fff93": [
      22
    ],
    "2c16e007": [
      16,
      90,
      46,
      47
    ],
    "f67a5cc8": [
      22
    ],
    "636f6bd0": [
      16,
      90,
      46,
      47
    ],
    "f8ca415e": [
      17
    ],
    "dfadff74": [
      4,
      89,
      83,
      41,
      92,
      81,
      68,
      53,
      45,
      93,
      76,
      54,
      57,
      74,
      43,
      48,
      98,
      84,
      82,
      97,
      60,
      99
    ],
    "540e0096": [
      23,
      72,
      73,
      79
    ],
    "2fd3ed6d": [
      23,
      72,
      73,
      79
    ],
    "5f116e6e": [
      23,
      72,
      73,
      79
    ],
    "4d512f5e": [
      23,
      72,
      73,
      79
    ],
    "7e747433": [
      6
    ],
    "d2a130d0": [
      19,
      59,
      61,
      86,
      63,
      100,
      62,
      77,
      55,
      88,
      69,
      75,
      71,
      66,
      85,
      94
    ],
    "b8ed865c": [
      26,
      95
    ],
    "1249891f": [
      25,
      95
    ],
    "0847047d": [
      24,
      80
    ],
    "3dd19472": [
      22
    ],
    "0bbe1c69": [
      22
    ],
    "0836ca22": [
      22
    ],
    "3667e54a": [
      22
    ],
    "38fb32fa": [
      22
    ],
    "04e8c794": [
      22
    ],
    "71e7a8e0": [
      23,
      72,
      73,
      79
    ],
    "8b902074": [
      3,
      89,
      83,
      41,
      92,
      81,
      68,
      49,
      65,
      87,
      55,
      42,
      67,
      64,
      50,
      58,
      52,
      91
    ],
    "b71cce48": [
      16,
      90,
      46,
      47
    ],
    "4e53d76f": [
      16,
      90,
      46,
      47
    ],
    "1b31f82a": [
      23,
      72,
      73,
      79
    ],
    "eded2aa6": [
      16,
      90,
      46,
      47
    ],
    "203b5a60": [
      16,
      90,
      46,
      47
    ],
    "23b5b149": [
      16,
      90,
      46,
      47
    ],
    "7e4b5898": [
      22
    ],
    "24b18a52": [
      22
    ],
    "81c06794": [
      22
    ],
    "54da2b01": [
      22
    ],
    "a6ec83be": [
      22
    ],
    "ebeb8538": [
      22
    ],
    "af41d8a6": [
      22
    ],
    "39221d26": [
      22
    ],
    "14caae78": [
      22
    ],
    "7672a46c": [
      22
    ],
    "747807ea": [
      16,
      90,
      46,
      47
    ],
    "5413d0d2": [
      16,
      90,
      46,
      47
    ],
    "4469526b": [
      17
    ],
    "bbb084d0": [
      17
    ],
    "7db5b334": [
      4,
      89,
      83,
      41,
      92,
      81,
      68,
      53,
      45,
      93,
      76,
      54,
      57,
      74,
      43,
      48,
      98,
      84,
      82,
      97,
      60,
      99
    ],
    "bf983128": [
      4,
      89,
      83,
      41,
      92,
      81,
      68,
      53,
      45,
      93,
      76,
      54,
      57,
      74,
      43,
      48,
      98,
      84,
      82,
      97,
      60,
      99
    ],
    "6e77cd5f": [
      4,
      89,
      83,
      41,
      92,
      81,
      68,
      53,
      45,
      93,
      76,
      54,
      57,
      74,
      43,
      48,
      98,
      84,
      82,
      97,
      60,
      99
    ],
    "73442f2f": [
      23,
      72,
      73,
      79
    ],
    "5d2d62c6": [
      23,
      72,
      73,
      79
    ],
    "63de1d90": [
      23,
      72,
      73,
      79
    ],
    "68466abc": [
      23,
      72,
      73,
      79
    ],
    "4379422f": [
      23,
      72,
      73,
      79
    ],
    "baae6ff2": [
      23,
      72,
      73,
      79
    ],
    "2dd0def4": [
      23,
      72,
      73,
      79
    ],
    "67556c3b": [
      23,
      72,
      73,
      79
    ],
    "7c6d733a": [
      23,
      72,
      73,
      79
    ],
    "87fbc260": [
      23,
      72,
      73,
      79
    ],
    "facf3712": [
      23,
      72,
      73,
      79
    ],
    "ae4eb62c": [
      23,
      72,
      73,
      79
    ],
    "633d734d": [
      6
    ],
    "9abc370c": [
      6
    ],
    "6a3a6844": [
      19,
      59,
      61,
      86,
      63,
      100,
      62,
      77,
      55,
      88,
      69,
      75,
      71,
      66,
      85,
      94
    ],
    "6a487fc5": [
      19,
      59,
      61,
      86,
      63,
      100,
      62,
      77,
      55,
      88,
      69,
      75,
      71,
      66,
      85,
      94
    ],
    "6a569746": [
      19,
      59,
      61,
      86,
      63,
      100,
      62,
      77,
      55,
      88,
      69,
      75,
      71,
      66,
      85,
      94
    ],
    "6a64aec7": [
      19,
      59,
      61,
      86,
      63,
      100,
      62,
      77,
      55,
      88,
      69,
      75,
      71,
      66,
      85,
      94
    ],
    "6a72c648": [
      19,
      59,
      61,
      86,
      63,
      100,
      62,
      77,
      55,
      88,
      69,
      75,
      71,
      66,
      85,
      94
    ],
    "6a80ddc9": [
      19,
      59,
      61,
      86,
      63,
      100,
      62,
      77,
      55,
      88,
      69,
      75,
      71,
      66,
      85,
      94
    ],
    "ebcc8bfa": [
      19,
      59,
      61,
      86,
      63,
      100,
      62,
      77,
      55,
      88,
      69,
      75,
      71,
      66,
      85,
      94
    ],
    "eb77fef4": [
      19,
      59,
      61,
      86,
      63,
      100,
      62,
      77,
      55,
      88,
      69,
      75,
      71,
      66,
      85,
      94
    ],
    "eb5bcff2": [
      19,
      59,
      61,
      86,
      63,
      100,
      62,
      77,
      55,
      88,
      69,
      75,
      71,
      66,
      85,
      94
    ],
    "eb2371ee": [
      19,
      59,
      61,
      86,
      63,
      100,
      62,
      77,
      55,
      88,
      69,
      75,
      71,
      66,
      85,
      94
    ],
    "8dcb628e": [
      19,
      59,
      61,
      86,
      63,
      100,
      62,
      77,
      55,
      88,
      69,
      75,
      71,
      66,
      85,
      94
    ],
    "8daf338c": [
      19,
      59,
      61,
      86,
      63,
      100,
      62,
      77,
      55,
      88,
      69,
      75,
      71,
      66,
      85,
      94
    ],
    "8d224882": [
      19,
      59,
      61,
      86,
      63,
      100,
      62,
      77,
      55,
      88,
      69,
      75,
      71,
      66,
      85,
      94
    ],
    "8a29534c": [
      19,
      59,
      61,
      86,
      63,
      100,
      62,
      77,
      55,
      88,
      69,
      75,
      71,
      66,
      85,
      94
    ],
    "89f0f548": [
      19,
      59,
      61,
      86,
      63,
      100,
      62,
      77,
      55,
      88,
      69,
      75,
      71,
      66,
      85,
      94
    ],
    "aed1109c": [
      19,
      59,
      61,
      86,
      63,
      100,
      62,
      77,
      55,
      88,
      69,
      75,
      71,
      66,
      85,
      94
    ],
    "0f06fd42": [
      19,
      59,
      61,
      86,
      63,
      100,
      62,
      77,
      55,
      88,
      69,
      75,
      71,
      66,
      85,
      94
    ],
    "b956da28": [
      26,
      95
    ],
    "4f40c0ce": [
      26,
      95
    ],
    "2b0e07c5": [
      25,
      95
    ],
    "3d483178": [
      25,
      95
    ],
    "4168de30": [
      24,
      80
    ],
    "380aa707": [
      24,
      80
    ],
    "303484d2": [
      24,
      80
    ],
    "5210abc4": [
      24,
      80
    ],
    "a88b0694": [
      5,
      83,
      78,
      53,
      45,
      93,
      76,
      54,
      57,
      74,
      43,
      48,
      98,
      84,
      82,
      97,
      60,
      99,
      96,
      56,
      44
    ],
    "344ded37": [
      5,
      83,
      78,
      53,
      45,
      93,
      76,
      54,
      57,
      74,
      43,
      48,
      98,
      84,
      82,
      97,
      60,
      99,
      96,
      56,
      44
    ],
    "4d59b37e": [
      5,
      83,
      78,
      53,
      45,
      93,
      76,
      54,
      57,
      74,
      43,
      48,
      98,
      84,
      82,
      97,
      60,
      99,
      96,
      56,
      44
    ],
    "d373d8a8": [
      5,
      83,
      78,
      53,
      45,
      93,
      76,
      54,
      57,
      74,
      43,
      48,
      98,
      84,
      82,
      97,
      60,
      99,
      96,
      56,
      44
    ],
    "bd72c40e": [
      5,
      83,
      78,
      53,
      45,
      93,
      76,
      54,
      57,
      74,
      43,
      48,
      98,
      84,
      82,
      97,
      60,
      99,
      96,
      56,
      44
    ],
    "86a8b7d4": [
      5,
      83,
      78,
      53,
      45,
      93,
      76,
      54,
      57,
      74,
      43,
      48,
      98,
      84,
      82,
      97,
      60,
      99,
      96,
      56,
      44
    ],
    "5778f72c": [
      5,
      83,
      78,
      53,
      45,
      93,
      76,
      54,
      57,
      74,
      43,
      48,
      98,
      84,
      82,
      97,
      60,
      99,
      96,
      56,
      44
    ],
    "087d22ad": [
      5,
      83,
      78,
      53,
      45,
      93,
      76,
      54,
      57,
      74,
      43,
      48,
      98,
      84,
      82,
      97,
      60,
      99,
      96,
      56,
      44
    ],
    "ebb05cf8": [
      3,
      89,
      83,
      41,
      92,
      81,
      68,
      49,
      65,
      87,
      55,
      42,
      67,
      64,
      50,
      58,
      52,
      91
    ],
    "90c457c4": [
      3,
      89,
      83,
      41,
      92,
      81,
      68,
      49,
      65,
      87,
      55,
      42,
      67,
      64,
      50,
      58,
      52,
      91
    ],
    "8d5aa686": [
      3,
      89,
      83,
      41,
      92,
      81,
      68,
      49,
      65,
      87,
      55,
      42,
      67,
      64,
      50,
      58,
      52,
      91
    ],
    "643cb336": [
      3,
      89,
      83,
      41,
      92,
      81,
      68,
      49,
      65,
      87,
      55,
      42,
      67,
      64,
      50,
      58,
      52,
      91
    ],
    "644acab7": [
      3,
      89,
      83,
      41,
      92,
      81,
      68,
      49,
      65,
      87,
      55,
      42,
      67,
      64,
      50,
      58,
      52,
      91
    ],
    "6466f9b9": [
      3,
      89,
      83,
      41,
      92,
      81,
      68,
      49,
      65,
      87,
      55,
      42,
      67,
      64,
      50,
      58,
      52,
      91
    ],
    "7b653a44": [
      3,
      89,
      83,
      41,
      92,
      81,
      68,
      49,
      65,
      87,
      55,
      42,
      67,
      64,
      50,
      58,
      52,
      91
    ],
    "fd8a14a4": [
      3,
      89,
      83,
      41,
      92,
      81,
      68,
      49,
      65,
      87,
      55,
      42,
      67,
      64,
      50,
      58,
      52,
      91
    ],
    "6c7896e5": [
      3,
      89,
      83,
      41,
      92,
      81,
      68,
      49,
      65,
      87,
      55,
      42,
      67,
      64,
      50,
      58,
      52,
      91
    ],
    "d3f53296": [
      21
    ],
    "1f040cf8": [
      8
    ],
    "7bead0d4": [
      9,
      89,
      78
    ],
    "88e0ee16": [
      4,
      89,
      83,
      41,
      92,
      81,
      68,
      53,
      45,
      93,
      76,
      54,
      57,
      74,
      43,
      48,
      98,
      84,
      82,
      97,
      60,
      99
    ],
    "3d809c2c": [
      17
    ],
    "733c9b04": [
      3,
      89,
      83,
      41,
      92,
      81,
      68,
      49,
      65,
      87,
      55,
      42,
      67,
      64,
      50,
      58,
      52,
      91
    ],
    "34fd8343": [
      28,
      89
    ],
    "08a362c0": [
      18,
      90
    ],
    "22d2aa24": [
      29,
      90,
      46
    ],
    "70420f88": [
      5,
      83,
      78,
      53,
      45,
      93,
      76,
      54,
      57,
      74,
      43,
      48,
      98,
      84,
      82,
      97,
      60,
      99,
      96,
      56,
      44
    ],
    "41897a6b": [
      24,
      80
    ],
    "d744e152": [
      25,
      95
    ],
    "252bddf0": [
      26,
      95
    ],
    "27f080fc": [
      19,
      59,
      61,
      86,
      63,
      100,
      62,
      77,
      55,
      88,
      69,
      75,
      71,
      66,
      85,
      94
    ],
    "2f5773ce": [
      15
    ],
    "837a8a4e": [
      12
    ],
    "0280803e": [
      6
    ],
    "2f41ffc6": [
      27,
      89
    ],
    "3c7dcd42": [
      13
    ],
    "7fe1e5b2": [
      7
    ],
    "c8c7ff90": [
      11
    ]
  },
  "assetsMapping": {
    "0a3100c339489669dba1.js": "7ea1d828",
    "0af5d0ab150860e3e852.js": "3cdf16e1",
    "0d469acb952b50d74a51.js": "5d0374e2",
    "1178d6a16637639c6322.js": "f107bf08",
    "3578ba861343c7822af0.js": "4130adce",
    "3acb8a5b88c508215a21.js": "13e965b2",
    "3c8c630d76d015350d3d.js": "bba68bf6",
    "503e96520cc8399a3037.js": "ccf5a1d8",
    "50b2eb2ad4a3a87cd04a.js": "0859c165",
    "52c7728e5c2baecebdd8.js": "c88a843c",
    "65ac612a5a2cf01a309e.js": "4cd8e659",
    "66de2dd2e7beaab61fe3.js": "0fa3071f",
    "66fffd8b7c939dd1aaf4.js": "1a3ae26b",
    "774db39ddff74922fb05.js": "6a0059ab",
    "7a0733979bbe84a7d86f.js": "07f547d9",
    "89d15c7d103b073c2b05.js": "b1bd4e12",
    "9847b64a3b614e0e576e.js": "291674d0",
    "9d4848e03a6dec37f133.js": "391baecc",
    "a43d0debf23d9ea0d825.js": "7e7ed9a2",
    "b6dc80c64d13afbe158b.js": "1c608406",
    "b81ccab56f54fcfdad13.js": "36cfadc9",
    "b93c66e12303cfaf5c87.js": "d5cb1bd6",
    "c02fdc94054a51c1a13b.js": "4ebe1efa",
    "c7edbe7565aa4800b1e2.js": "64dbf1d5",
    "c81fe281f7ddf8114954.js": "02c4b1f4",
    "d333d2891aaa1fb920fc.js": "8e550326",
    "f3dcc8362db3072f2d9d.js": "8650e37e",
    "f6f3898f57f41ef05482.js": "6fca0322"
  }
}